animeinfo/__init__.py
animeinfo/anime_library.py
animesearchinfo-0.0.1.dist-info/LICENSE.txt
animesearchinfo-0.0.1.dist-info/METADATA
animesearchinfo-0.0.1.dist-info/WHEEL
animesearchinfo-0.0.1.dist-info/top_level.txt
animesearchinfo-0.0.1.dist-info/RECORD
