Metadata-Version: 2.1
Name: animesearchinfo
Version: 0.0.1
Summary: Short info about some anime.
Home-page: https://github.com/shaaa-xq/animesearchinfo
Author: shaaa
Author-email: <ayeshacha177@gmail.com>
License: MIT
Keywords: animesearch,anime,anime search info,animesearchinfo
Classifier: Development Status :: 1 - Planning
License-File: LICENSE.txt
